numbacs/__init__.py
numbacs/diagnostics.py
numbacs/flows.py
numbacs/integration.py
numbacs/utils.py
numbacs/extraction/__init__.py
numbacs/extraction/elliptic.py
numbacs/extraction/hyperbolic.py
numbacs/extraction/ridges.py
numbacs-0.1.1.dist-info/METADATA
numbacs-0.1.1.dist-info/WHEEL
numbacs-0.1.1.dist-info/licenses/LICENSE
numbacs-0.1.1.dist-info/RECORD
