Metadata-Version: 2.3
Name: numbacs
Version: 0.1.1
Summary: Numba accelerated coherent structure package.
Project-URL: Documentation, https://numbacs.readthedocs.io/
Project-URL: Issues, https://github.com/alb3rtjarvis/numbacs/issues
Project-URL: Source, https://github.com/alb3rtjarvis/numbacs
Author-email: alb3rtjarvis <ajarvis@vt.edu>
License-Expression: MPL-2.0
License-File: LICENSE
Classifier: License :: OSI Approved :: Mozilla Public License 2.0 (MPL 2.0)
Classifier: Operating System :: OS Independent
Classifier: Programming Language :: Python :: 3.10
Classifier: Programming Language :: Python :: 3.11
Requires-Python: <3.12,>=3.10
Requires-Dist: contourpy
Requires-Dist: interpolation>=2.2.6
Requires-Dist: numba
Requires-Dist: numbalsoda
Requires-Dist: numpy
Requires-Dist: scipy
